{
  "JSON_SCHEMA_VERSION": "1.1",

  "PACKAGE_NAME": "KAS-1.0",

  "SHELL_COMPILE_BINARY_SCRIPT" : "make_binary-1.0.cmd",

  "RELEASE_NAME_FREE_FORMAT" : "KAS_v{0}.{1}_beta7",

  "STRUCTURE" : {
    "" : [
      "/README.md",
      "/LICENSE-1.0.md",
      "/Lang",
      "/Models",
      "/Parts",
      "/Patches",
      "/Sounds",
      "/Textures"
    ],
    "Plugins" : [
      "{COMPILED_BINARY}",
      "bin/Release/{PACKAGE_NAME}.xml",
      "{MINIAVC_VERSION_FILE}",
      "/Binaries/*"
    ]
  }
}
